bot/__init__.py
bot/core.py
bot/handlers.py
bot/settings.py
telegram_bot_framework_bolt-0.1.0.dist-info/METADATA
telegram_bot_framework_bolt-0.1.0.dist-info/WHEEL
telegram_bot_framework_bolt-0.1.0.dist-info/top_level.txt
telegram_bot_framework_bolt-0.1.0.dist-info/RECORD
