Metadata-Version: 2.1
Name: telegram-bot-framework-bolt
Version: 0.1.0
Summary: A powerful and extensible Python-based Telegram bot framework
Home-page: https://github.com/gersonfreire/telegram_framework_bolt
Author: Maker
Author-email: gerson.freire@gmail.com
Classifier: Programming Language :: Python :: 3
Classifier: License :: OSI Approved :: MIT License
Classifier: Operating System :: OS Independent
Requires-Python: >=3.6
Requires-Dist: python-telegram-bot>=20.7
Requires-Dist: python-dotenv>=1.0.0
Requires-Dist: pyyaml>=6.0.1
